LICENSE
MANIFEST.in
README.md
setup.py
quantumnetworks/VERSION.txt
quantumnetworks/__init__.py
quantumnetworks.egg-info/PKG-INFO
quantumnetworks.egg-info/SOURCES.txt
quantumnetworks.egg-info/dependency_links.txt
quantumnetworks.egg-info/requires.txt
quantumnetworks.egg-info/top_level.txt
quantumnetworks/analysis/__init__.py
quantumnetworks/analysis/error.py
quantumnetworks/analysis/performance.py
quantumnetworks/analysis/quantities/__init__.py
quantumnetworks/analysis/quantities/base.py
quantumnetworks/analysis/quantities/coherent.py
quantumnetworks/analysis/quantities/stats.py
quantumnetworks/systems/__init__.py
quantumnetworks/systems/base.py
quantumnetworks/systems/doublemode.py
quantumnetworks/systems/exponential.py
quantumnetworks/systems/multimode.py
quantumnetworks/systems/singlemode.py
quantumnetworks/utils/__init__.py
quantumnetworks/utils/visualization.py