Metadata-Version: 2.1
Name: quantumnetworks
Version: 0.1.0
Summary: Quantum Networks
Home-page: https://github.com/Phionx/quantumnetworks
Author: Shantanu Jha, Shoumik Chowdhury, Lamia Ateshian
Author-email: shantanu.rajesh.jha@gmail.com
License: MIT
Project-URL: Bug Tracker, https://github.com/Phionx/quantumnetworks/issues
Project-URL: Documentation, https://github.com/Phionx/quantumnetworks
Project-URL: Source Code, https://github.com/Phionx/quantumnetworks
Project-URL: Demos, https://github.com/Phionx/quantumnetworks/tree/master/demos
Project-URL: Tests, https://github.com/Phionx/quantumnetworks/tree/master/tests
Keywords: quantum networks communication computing
Platform: UNKNOWN
Classifier: Environment :: Console
Classifier: License :: OSI Approved :: MIT License
Classifier: Intended Audience :: Developers
Classifier: Intended Audience :: Science/Research
Classifier: Operating System :: Microsoft :: Windows
Classifier: Operating System :: MacOS :: MacOS X
Classifier: Operating System :: POSIX :: Linux
Classifier: Programming Language :: Python :: 3 :: Only
Classifier: Programming Language :: Python :: 3.6
Classifier: Programming Language :: Python :: 3.7
Classifier: Programming Language :: Python :: 3.8
Classifier: Topic :: Scientific/Engineering
Requires-Python: >=3.6
Provides-Extra: dev
